cartogram/__init__.py
cartogram/cartogram.py
cartogram-1.0.2.dist-info/licenses/LICENSE
cartogram-1.0.2.dist-info/METADATA
cartogram-1.0.2.dist-info/WHEEL
cartogram-1.0.2.dist-info/top_level.txt
cartogram-1.0.2.dist-info/RECORD
