Metadata-Version: 2.4
Name: cartogram
Version: 1.0.2
Summary: Compute continous cartograms (anamorphic maps)
Author-email: Christoph Fink <christoph.fink@christophfink.com>
License: GPL-3.0-or-later
Project-URL: Documentation, https://python-cartogram.readthedocs.org/
Project-URL: Repository, https://github.com/austromorph/python-cartogram
Project-URL: Change log, https://github.com/austromorph/python-cartogram/blob/main/CHANGELOG.md
Project-URL: Bug tracker, https://github.com/austromorph/python-cartogram/issues
Keywords: cartography,geodata,geoinformation,visualisation
Classifier: Programming Language :: Python :: 3
Classifier: License :: OSI Approved :: GNU General Public License v3 (GPLv3)
Classifier: Operating System :: OS Independent
Requires-Python: >=3.10
License-File: LICENSE
Requires-Dist: geopandas
Requires-Dist: joblib
Requires-Dist: numpy
Requires-Dist: pandas
Requires-Dist: shapely
Provides-Extra: dev
Requires-Dist: black; extra == "dev"
Requires-Dist: flake8; extra == "dev"
Requires-Dist: flake8-bugbear; extra == "dev"
Requires-Dist: flake8-pyproject; extra == "dev"
Requires-Dist: isort; extra == "dev"
Requires-Dist: pydocstyle; extra == "dev"
Requires-Dist: pylint; extra == "dev"
Provides-Extra: docs
Requires-Dist: folium; extra == "docs"
Requires-Dist: GitPython; extra == "docs"
Requires-Dist: jupyterlab_myst; extra == "docs"
Requires-Dist: mapclassify; extra == "docs"
Requires-Dist: matplotlib; extra == "docs"
Requires-Dist: myst-nb; extra == "docs"
Requires-Dist: nbsphinx; extra == "docs"
Requires-Dist: pybtex-apa7-style; extra == "docs"
Requires-Dist: sphinx; extra == "docs"
Requires-Dist: sphinx-book-theme; extra == "docs"
Requires-Dist: sphinx-design; extra == "docs"
Requires-Dist: sphinxcontrib-bibtex; extra == "docs"
Requires-Dist: sphinxcontrib-images; extra == "docs"
Requires-Dist: xyzservices; extra == "docs"
Provides-Extra: tests
Requires-Dist: pytest; extra == "tests"
Requires-Dist: pytest-cov; extra == "tests"
Requires-Dist: pytest-lazy-fixtures; extra == "tests"
Dynamic: license-file
